simplio/__init__.py
simplio/simplio.py
simplio-0.1.1.dist-info/DESCRIPTION.rst
simplio-0.1.1.dist-info/METADATA
simplio-0.1.1.dist-info/metadata.json
simplio-0.1.1.dist-info/RECORD
simplio-0.1.1.dist-info/top_level.txt
simplio-0.1.1.dist-info/WHEEL
