Metadata-Version: 2.0
Name: simplio
Version: 0.1.1
Summary: Simplest-case command-line input/output
Home-page: https://github.com/josephl/simplio
Author: Joseph Lee
Author-email: joe.lee.three.thousand@gmail.com
License: MIT
Keywords: input output file io
Platform: UNKNOWN
